Metadata-Version: 2.1
Name: largestLogger
Version: 1.1.1
Summary: A simple, open source logging library. It can be easily added to a program and provides a colourful, reliable and managed logging system to your application/script! https://github.com/LargestBoi/largestLogger
Author: LargestBoi
